{"nodes": [{"id": "src_components_notes_notesfeed_tsx", "label": "NotesFeed.tsx", "file_type": "code", "source_file": "src\\components\\notes\\NotesFeed.tsx", "source_location": "L1"}, {"id": "notesfeed_handledelete", "label": "handleDelete()", "file_type": "code", "source_file": "src\\components\\notes\\NotesFeed.tsx", "source_location": "L18"}, {"id": "notesfeed_formatdate", "label": "formatDate()", "file_type": "code", "source_file": "src\\components\\notes\\NotesFeed.tsx", "source_location": "L23"}], "edges": [{"source": "src_components_notes_notesfeed_tsx", "target": "auth", "relation": "imports_from", "confidence": "EXTRACTED", "source_file": "src\\components\\notes\\NotesFeed.tsx", "source_location": "L1", "weight": 1.0}, {"source": "src_components_notes_notesfeed_tsx", "target": "use_notes", "relation": "imports_from", "confidence": "EXTRACTED", "source_file": "src\\components\\notes\\NotesFeed.tsx", "source_location": "L2", "weight": 1.0}, {"source": "src_components_notes_notesfeed_tsx", "target": "lucide_react", "relation": "imports_from", "confidence": "EXTRACTED", "source_file": "src\\components\\notes\\NotesFeed.tsx", "source_location": "L3", "weight": 1.0}, {"source": "src_components_notes_notesfeed_tsx", "target": "database", "relation": "imports_from", "confidence": "EXTRACTED", "source_file": "src\\components\\notes\\NotesFeed.tsx", "source_location": "L4", "weight": 1.0}, {"source": "src_components_notes_notesfeed_tsx", "target": "notesfeed_handledelete", "relation": "contains", "confidence": "EXTRACTED", "source_file": "src\\components\\notes\\NotesFeed.tsx", "source_location": "L18", "weight": 1.0}, {"source": "src_components_notes_notesfeed_tsx", "target": "notesfeed_formatdate", "relation": "contains", "confidence": "EXTRACTED", "source_file": "src\\components\\notes\\NotesFeed.tsx", "source_location": "L23", "weight": 1.0}]}